AUTHORS.rst
LICENSE
MANIFEST.in
README.rst
requirements-dev.txt
requirements.txt
setup.cfg
setup.py
share/data/sunspot.dat
share/data/sunspot_monthly.dat
src/cpp/__init__.py
src/cpp/mydpss.c
src/spectrum/__init__.py
src/spectrum/arma.py
src/spectrum/burg.py
src/spectrum/cholesky.py
src/spectrum/cohere.py
src/spectrum/correlation.py
src/spectrum/correlog.py
src/spectrum/covar.py
src/spectrum/criteria.py
src/spectrum/datasets.py
src/spectrum/eigen.py
src/spectrum/eigenfre.py
src/spectrum/errors.py
src/spectrum/levinson.py
src/spectrum/linalg.py
src/spectrum/linear_prediction.py
src/spectrum/lpc.py
src/spectrum/minvar.py
src/spectrum/modcovar.py
src/spectrum/mtm.py
src/spectrum/periodogram.py
src/spectrum/psd.py
src/spectrum/toeplitz.py
src/spectrum/tools.py
src/spectrum/transfer.py
src/spectrum/waveform.py
src/spectrum/window.py
src/spectrum/yulewalker.py
src/spectrum.egg-info/PKG-INFO
src/spectrum.egg-info/SOURCES.txt
src/spectrum.egg-info/dependency_links.txt
src/spectrum.egg-info/requires.txt
src/spectrum.egg-info/top_level.txt
test/test_arma.py
test/test_burg.py
test/test_cholesky.py
test/test_correlation.py
test/test_correlog.py
test/test_covar.py
test/test_criteria.py
test/test_datasets.py
test/test_eigen.py
test/test_eigenfre.py
test/test_errors.py
test/test_levinson.py
test/test_linalg.py
test/test_linear_prediction.py
test/test_lms.py
test/test_lpc.py
test/test_minvar.py
test/test_modcovar.py
test/test_mtm.py
test/test_periodogram.py
test/test_psd.py
test/test_spectrum.py
test/test_toeplitz.py
test/test_tools.py
test/test_transfer.py
test/test_waveform.py
test/test_window.py
test/test_yulewalker.py