Metadata-Version: 1.1
Name: spectrum
Version: 0.6.8
Summary: Spectrum Analysis Tools
Home-page: http://github.com/cokelaer/spectrum
Author: Thomas Cokelaer
Author-email: cokelaer@gmail.com
License: new BSD
Platform: Linux
Classifier: Development Status :: 1 - Planning
Classifier: Environment :: Console
Classifier: Intended Audience :: Developers
Classifier: Intended Audience :: Education
Classifier: Intended Audience :: Financial and Insurance Industry
Classifier: Intended Audience :: Information Technology
Classifier: Intended Audience :: Science/Research
Classifier: Intended Audience :: Telecommunications Industry
Classifier: License :: OSI Approved :: BSD License
Classifier: Operating System :: POSIX :: Linux
Classifier: Operating System :: Unix
Classifier: Programming Language :: Python :: 2.7
Classifier: Programming Language :: Python :: 3.5
Classifier: Programming Language :: Python :: 3.6
Classifier: Topic :: Scientific/Engineering
